LICENSE
MANIFEST.in
README.rst
setup.py
hostproof_auth/__init__.py
hostproof_auth/auth.py
hostproof_auth/models.py
hostproof_auth/urls.py
hostproof_auth/utils.py
hostproof_auth/views.py
hostproof_auth.egg-info/PKG-INFO
hostproof_auth.egg-info/SOURCES.txt
hostproof_auth.egg-info/dependency_links.txt
hostproof_auth.egg-info/not-zip-safe
hostproof_auth.egg-info/requires.txt
hostproof_auth.egg-info/top_level.txt
hostproof_auth/static/hostproof_auth/hostproof_auth.js
hostproof_auth/static/hostproof_auth/jquery-2.0.3.min.js
hostproof_auth/static/hostproof_auth/sjcl.js